light2/__init__.py
light2/light.py
light2/tm.py
light2-2.2.dist-info/METADATA
light2-2.2.dist-info/RECORD
light2-2.2.dist-info/WHEEL
light2-2.2.dist-info/top_level.txt
