Metadata-Version: 2.1
Name: light2
Version: 2.2
Summary: A light flask
Home-page: https://github.com/pypa/sampleproject
Author: cyr
Author-email: 15501766562@163.com
License: UNKNOWN
Platform: UNKNOWN
Classifier: Programming Language :: Python :: 3
Classifier: License :: OSI Approved :: MIT License
Classifier: Operating System :: OS Independent
